{
    "1245104789017329695": [
        {
            "author_id": 1368624014364512287,
            "author_name": "GitHub#0000",
            "author_avatar": "https://cdn.discordapp.com/avatars/1368624014364512287/df91181b3f1cf0ef1592fbe18e0962d7.png?size=1024",
            "is_bot": true,
            "content": "",
            "created_at": "2025-08-20T18:46:25.063000+00:00",
            "is_webhook": false,
            "attachments": [],
            "embeds": [
                {
                    "author": {
                        "name": "XXMAAXX",
                        "url": "https://github.com/XXMAAXX",
                        "icon_url": "https://avatars.githubusercontent.com/u/145601904?v=4",
                        "proxy_icon_url": "https://images-ext-1.discordapp.net/external/LrJoeFfhmNQcmM0wh9fZn3ntJnyJQBts-XWzR21NrcU/%3Fv%3D4/https/avatars.githubusercontent.com/u/145601904"
                    },
                    "flags": 0,
                    "color": 7506394,
                    "type": "rich",
                    "description": "[`af309ad`](https://github.com/OverX-System/data/commit/af309adc7da37bc6f779ed6795cf5d3839822b88) Update data_channel_messages/messages_backup_12... - XXMAAXX",
                    "url": "https://github.com/OverX-System/data/commit/af309adc7da37bc6f779ed6795cf5d3839822b88",
                    "title": "[data:main] 1 new commit"
                }
            ]
        },
        {
            "author_id": 1368624014364512287,
            "author_name": "GitHub#0000",
            "author_avatar": "https://cdn.discordapp.com/avatars/1368624014364512287/df91181b3f1cf0ef1592fbe18e0962d7.png?size=1024",
            "is_bot": true,
            "content": "",
            "created_at": "2025-08-20T18:46:24.205000+00:00",
            "is_webhook": false,
            "attachments": [],
            "embeds": [
                {
                    "author": {
                        "name": "XXMAAXX",
                        "url": "https://github.com/XXMAAXX",
                        "icon_url": "https://avatars.githubusercontent.com/u/145601904?v=4",
                        "proxy_icon_url": "https://images-ext-1.discordapp.net/external/LrJoeFfhmNQcmM0wh9fZn3ntJnyJQBts-XWzR21NrcU/%3Fv%3D4/https/avatars.githubusercontent.com/u/145601904"
                    },
                    "flags": 0,
                    "color": 7506394,
                    "type": "rich",
                    "description": "[`6fc1156`](https://github.com/OverX-System/data/commit/6fc1156981c3da2898e2423b94048dc7a56107fd) Update data_channel_messages/messages_backup_12... - XXMAAXX",
                    "url": "https://github.com/OverX-System/data/commit/6fc1156981c3da2898e2423b94048dc7a56107fd",
                    "title": "[data:main] 1 new commit"
                }
            ]
        },
        {
            "author_id": 1368624014364512287,
            "author_name": "GitHub#0000",
            "author_avatar": "https://cdn.discordapp.com/avatars/1368624014364512287/df91181b3f1cf0ef1592fbe18e0962d7.png?size=1024",
            "is_bot": true,
            "content": "",
            "created_at": "2025-08-20T18:46:21.060000+00:00",
            "is_webhook": false,
            "attachments": [],
            "embeds": [
                {
                    "author": {
                        "name": "XXMAAXX",
                        "url": "https://github.com/XXMAAXX",
                        "icon_url": "https://avatars.githubusercontent.com/u/145601904?v=4",
                        "proxy_icon_url": "https://images-ext-1.discordapp.net/external/LrJoeFfhmNQcmM0wh9fZn3ntJnyJQBts-XWzR21NrcU/%3Fv%3D4/https/avatars.githubusercontent.com/u/145601904"
                    },
                    "flags": 0,
                    "color": 7506394,
                    "type": "rich",
                    "description": "[`79d683e`](https://github.com/OverX-System/data/commit/79d683e40185ae52f74f6c7e9daa7a6ccff153f0) Update data_channel_messages/messages_backup_12... - XXMAAXX",
                    "url": "https://github.com/OverX-System/data/commit/79d683e40185ae52f74f6c7e9daa7a6ccff153f0",
                    "title": "[data:main] 1 new commit"
                }
            ]
        },
        {
            "author_id": 1368624014364512287,
            "author_name": "GitHub#0000",
            "author_avatar": "https://cdn.discordapp.com/avatars/1368624014364512287/df91181b3f1cf0ef1592fbe18e0962d7.png?size=1024",
            "is_bot": true,
            "content": "",
            "created_at": "2025-08-20T18:46:20.861000+00:00",
            "is_webhook": false,
            "attachments": [],
            "embeds": [
                {
                    "author": {
                        "name": "XXMAAXX",
                        "url": "https://github.com/XXMAAXX",
                        "icon_url": "https://avatars.githubusercontent.com/u/145601904?v=4",
                        "proxy_icon_url": "https://images-ext-1.discordapp.net/external/LrJoeFfhmNQcmM0wh9fZn3ntJnyJQBts-XWzR21NrcU/%3Fv%3D4/https/avatars.githubusercontent.com/u/145601904"
                    },
                    "flags": 0,
                    "color": 7506394,
                    "type": "rich",
                    "description": "[`61c3fb6`](https://github.com/OverX-System/data/commit/61c3fb6167ce0ea3c8f64289c08244090e6805ff) Delete data_backups/databackups directory - XXMAAXX",
                    "url": "https://github.com/OverX-System/data/commit/61c3fb6167ce0ea3c8f64289c08244090e6805ff",
                    "title": "[data:main] 1 new commit"
                }
            ]
        },
        {
            "author_id": 1368624014364512287,
            "author_name": "GitHub#0000",
            "author_avatar": "https://cdn.discordapp.com/avatars/1368624014364512287/df91181b3f1cf0ef1592fbe18e0962d7.png?size=1024",
            "is_bot": true,
            "content": "",
            "created_at": "2025-08-20T18:46:20.310000+00:00",
            "is_webhook": false,
            "attachments": [],
            "embeds": [
                {
                    "author": {
                        "name": "XXMAAXX",
                        "url": "https://github.com/XXMAAXX",
                        "icon_url": "https://avatars.githubusercontent.com/u/145601904?v=4",
                        "proxy_icon_url": "https://images-ext-1.discordapp.net/external/LrJoeFfhmNQcmM0wh9fZn3ntJnyJQBts-XWzR21NrcU/%3Fv%3D4/https/avatars.githubusercontent.com/u/145601904"
                    },
                    "flags": 0,
                    "color": 7506394,
                    "type": "rich",
                    "description": "[`9120326`](https://github.com/OverX-System/data/commit/91203266ddb8f594ececd36535eecb4163ab82fb) Update data_channel_messages/messages_backup_12... - XXMAAXX",
                    "url": "https://github.com/OverX-System/data/commit/91203266ddb8f594ececd36535eecb4163ab82fb",
                    "title": "[data:main] 1 new commit"
                }
            ]
        }
    ],
    "1212061522851921940": [
        {
            "author_id": 1364330195544313961,
            "author_name": "GitHub#0000",
            "author_avatar": "https://cdn.discordapp.com/avatars/1364330195544313961/df91181b3f1cf0ef1592fbe18e0962d7.png?size=1024",
            "is_bot": true,
            "content": "",
            "created_at": "2025-08-20T18:46:29.276000+00:00",
            "is_webhook": false,
            "attachments": [],
            "embeds": [
                {
                    "author": {
                        "name": "XXMAAXX",
                        "url": "https://github.com/XXMAAXX",
                        "icon_url": "https://avatars.githubusercontent.com/u/145601904?v=4",
                        "proxy_icon_url": "https://images-ext-1.discordapp.net/external/LrJoeFfhmNQcmM0wh9fZn3ntJnyJQBts-XWzR21NrcU/%3Fv%3D4/https/avatars.githubusercontent.com/u/145601904"
                    },
                    "flags": 0,
                    "color": 7506394,
                    "type": "rich",
                    "description": "[`7c50446`](https://github.com/OverX-System/data/commit/7c50446014114b0577519bf72a7f80226bc52175) Update data_channel_messages/messages_backup_12... - XXMAAXX",
                    "url": "https://github.com/OverX-System/data/commit/7c50446014114b0577519bf72a7f80226bc52175",
                    "title": "[data:main] 1 new commit"
                }
            ]
        },
        {
            "author_id": 1364330195544313961,
            "author_name": "GitHub#0000",
            "author_avatar": "https://cdn.discordapp.com/avatars/1364330195544313961/df91181b3f1cf0ef1592fbe18e0962d7.png?size=1024",
            "is_bot": true,
            "content": "",
            "created_at": "2025-08-20T18:46:27.741000+00:00",
            "is_webhook": false,
            "attachments": [],
            "embeds": [
                {
                    "author": {
                        "name": "XXMAAXX",
                        "url": "https://github.com/XXMAAXX",
                        "icon_url": "https://avatars.githubusercontent.com/u/145601904?v=4",
                        "proxy_icon_url": "https://images-ext-1.discordapp.net/external/LrJoeFfhmNQcmM0wh9fZn3ntJnyJQBts-XWzR21NrcU/%3Fv%3D4/https/avatars.githubusercontent.com/u/145601904"
                    },
                    "flags": 0,
                    "color": 7506394,
                    "type": "rich",
                    "description": "[`c3f63a1`](https://github.com/OverX-System/data/commit/c3f63a1f984098fa0b18fa4b456bf58caff4b58b) Update data_channel_messages/messages_backup_12... - XXMAAXX",
                    "url": "https://github.com/OverX-System/data/commit/c3f63a1f984098fa0b18fa4b456bf58caff4b58b",
                    "title": "[data:main] 1 new commit"
                }
            ]
        },
        {
            "author_id": 1364330195544313961,
            "author_name": "GitHub#0000",
            "author_avatar": "https://cdn.discordapp.com/avatars/1364330195544313961/df91181b3f1cf0ef1592fbe18e0962d7.png?size=1024",
            "is_bot": true,
            "content": "",
            "created_at": "2025-08-20T18:46:26.635000+00:00",
            "is_webhook": false,
            "attachments": [],
            "embeds": [
                {
                    "author": {
                        "name": "XXMAAXX",
                        "url": "https://github.com/XXMAAXX",
                        "icon_url": "https://avatars.githubusercontent.com/u/145601904?v=4",
                        "proxy_icon_url": "https://images-ext-1.discordapp.net/external/LrJoeFfhmNQcmM0wh9fZn3ntJnyJQBts-XWzR21NrcU/%3Fv%3D4/https/avatars.githubusercontent.com/u/145601904"
                    },
                    "flags": 0,
                    "color": 7506394,
                    "type": "rich",
                    "description": "[`ab68da5`](https://github.com/OverX-System/data/commit/ab68da5c5fa49904b6cebe45031c068b9ea22372) Update data_channel_messages/messages_backup_12... - XXMAAXX",
                    "url": "https://github.com/OverX-System/data/commit/ab68da5c5fa49904b6cebe45031c068b9ea22372",
                    "title": "[data:main] 1 new commit"
                }
            ]
        },
        {
            "author_id": 1364330195544313961,
            "author_name": "GitHub#0000",
            "author_avatar": "https://cdn.discordapp.com/avatars/1364330195544313961/df91181b3f1cf0ef1592fbe18e0962d7.png?size=1024",
            "is_bot": true,
            "content": "",
            "created_at": "2025-08-20T18:46:25.074000+00:00",
            "is_webhook": false,
            "attachments": [],
            "embeds": [
                {
                    "author": {
                        "name": "XXMAAXX",
                        "url": "https://github.com/XXMAAXX",
                        "icon_url": "https://avatars.githubusercontent.com/u/145601904?v=4",
                        "proxy_icon_url": "https://images-ext-1.discordapp.net/external/LrJoeFfhmNQcmM0wh9fZn3ntJnyJQBts-XWzR21NrcU/%3Fv%3D4/https/avatars.githubusercontent.com/u/145601904"
                    },
                    "flags": 0,
                    "color": 7506394,
                    "type": "rich",
                    "description": "[`af309ad`](https://github.com/OverX-System/data/commit/af309adc7da37bc6f779ed6795cf5d3839822b88) Update data_channel_messages/messages_backup_12... - XXMAAXX",
                    "url": "https://github.com/OverX-System/data/commit/af309adc7da37bc6f779ed6795cf5d3839822b88",
                    "title": "[data:main] 1 new commit"
                }
            ]
        },
        {
            "author_id": 1364330195544313961,
            "author_name": "GitHub#0000",
            "author_avatar": "https://cdn.discordapp.com/avatars/1364330195544313961/df91181b3f1cf0ef1592fbe18e0962d7.png?size=1024",
            "is_bot": true,
            "content": "",
            "created_at": "2025-08-20T18:46:24.156000+00:00",
            "is_webhook": false,
            "attachments": [],
            "embeds": [
                {
                    "author": {
                        "name": "XXMAAXX",
                        "url": "https://github.com/XXMAAXX",
                        "icon_url": "https://avatars.githubusercontent.com/u/145601904?v=4",
                        "proxy_icon_url": "https://images-ext-1.discordapp.net/external/LrJoeFfhmNQcmM0wh9fZn3ntJnyJQBts-XWzR21NrcU/%3Fv%3D4/https/avatars.githubusercontent.com/u/145601904"
                    },
                    "flags": 0,
                    "color": 7506394,
                    "type": "rich",
                    "description": "[`6fc1156`](https://github.com/OverX-System/data/commit/6fc1156981c3da2898e2423b94048dc7a56107fd) Update data_channel_messages/messages_backup_12... - XXMAAXX",
                    "url": "https://github.com/OverX-System/data/commit/6fc1156981c3da2898e2423b94048dc7a56107fd",
                    "title": "[data:main] 1 new commit"
                }
            ]
        }
    ]
}