{
    "1212061522851921940": [
        {
            "author_id": 1364330195544313961,
            "author_name": "GitHub#0000",
            "author_avatar": "https://cdn.discordapp.com/avatars/1364330195544313961/df91181b3f1cf0ef1592fbe18e0962d7.png?size=1024",
            "is_bot": true,
            "content": "",
            "created_at": "2025-08-20T18:52:43.738000+00:00",
            "is_webhook": false,
            "attachments": [],
            "embeds": [
                {
                    "author": {
                        "name": "XXMAAXX",
                        "url": "https://github.com/XXMAAXX",
                        "icon_url": "https://avatars.githubusercontent.com/u/145601904?v=4",
                        "proxy_icon_url": "https://images-ext-1.discordapp.net/external/LrJoeFfhmNQcmM0wh9fZn3ntJnyJQBts-XWzR21NrcU/%3Fv%3D4/https/avatars.githubusercontent.com/u/145601904"
                    },
                    "flags": 0,
                    "color": 7506394,
                    "type": "rich",
                    "description": "[`a37efbf`](https://github.com/OverX-System/data/commit/a37efbfd3e954b98eb995510d19b8613c3a09449) Update data_channel_messages/messages_backup_12... - XXMAAXX",
                    "url": "https://github.com/OverX-System/data/commit/a37efbfd3e954b98eb995510d19b8613c3a09449",
                    "title": "[data:main] 1 new commit"
                }
            ]
        },
        {
            "author_id": 1364330195544313961,
            "author_name": "GitHub#0000",
            "author_avatar": "https://cdn.discordapp.com/avatars/1364330195544313961/df91181b3f1cf0ef1592fbe18e0962d7.png?size=1024",
            "is_bot": true,
            "content": "",
            "created_at": "2025-08-20T18:52:42.287000+00:00",
            "is_webhook": false,
            "attachments": [],
            "embeds": [
                {
                    "author": {
                        "name": "XXMAAXX",
                        "url": "https://github.com/XXMAAXX",
                        "icon_url": "https://avatars.githubusercontent.com/u/145601904?v=4",
                        "proxy_icon_url": "https://images-ext-1.discordapp.net/external/LrJoeFfhmNQcmM0wh9fZn3ntJnyJQBts-XWzR21NrcU/%3Fv%3D4/https/avatars.githubusercontent.com/u/145601904"
                    },
                    "flags": 0,
                    "color": 7506394,
                    "type": "rich",
                    "description": "[`45d8306`](https://github.com/OverX-System/data/commit/45d830641d744dd73f9ab6a03f8c5c753db1e674) Update data_channel_messages/messages_backup_12... - XXMAAXX",
                    "url": "https://github.com/OverX-System/data/commit/45d830641d744dd73f9ab6a03f8c5c753db1e674",
                    "title": "[data:main] 1 new commit"
                }
            ]
        },
        {
            "author_id": 1364330195544313961,
            "author_name": "GitHub#0000",
            "author_avatar": "https://cdn.discordapp.com/avatars/1364330195544313961/df91181b3f1cf0ef1592fbe18e0962d7.png?size=1024",
            "is_bot": true,
            "content": "",
            "created_at": "2025-08-20T18:52:41.076000+00:00",
            "is_webhook": false,
            "attachments": [],
            "embeds": [
                {
                    "author": {
                        "name": "XXMAAXX",
                        "url": "https://github.com/XXMAAXX",
                        "icon_url": "https://avatars.githubusercontent.com/u/145601904?v=4",
                        "proxy_icon_url": "https://images-ext-1.discordapp.net/external/LrJoeFfhmNQcmM0wh9fZn3ntJnyJQBts-XWzR21NrcU/%3Fv%3D4/https/avatars.githubusercontent.com/u/145601904"
                    },
                    "flags": 0,
                    "color": 7506394,
                    "type": "rich",
                    "description": "[`0308638`](https://github.com/OverX-System/data/commit/03086389eee4e7250b2dbb74957e44dd23de1623) Update data_channel_messages/messages_backup_12... - XXMAAXX",
                    "url": "https://github.com/OverX-System/data/commit/03086389eee4e7250b2dbb74957e44dd23de1623",
                    "title": "[data:main] 1 new commit"
                }
            ]
        },
        {
            "author_id": 1364330195544313961,
            "author_name": "GitHub#0000",
            "author_avatar": "https://cdn.discordapp.com/avatars/1364330195544313961/df91181b3f1cf0ef1592fbe18e0962d7.png?size=1024",
            "is_bot": true,
            "content": "",
            "created_at": "2025-08-20T18:52:39.346000+00:00",
            "is_webhook": false,
            "attachments": [],
            "embeds": [
                {
                    "author": {
                        "name": "XXMAAXX",
                        "url": "https://github.com/XXMAAXX",
                        "icon_url": "https://avatars.githubusercontent.com/u/145601904?v=4",
                        "proxy_icon_url": "https://images-ext-1.discordapp.net/external/LrJoeFfhmNQcmM0wh9fZn3ntJnyJQBts-XWzR21NrcU/%3Fv%3D4/https/avatars.githubusercontent.com/u/145601904"
                    },
                    "flags": 0,
                    "color": 7506394,
                    "type": "rich",
                    "description": "[`1cf37c0`](https://github.com/OverX-System/data/commit/1cf37c0f2104ce60efd51d39a8df685c7f12146f) Update data_channel_messages/messages_backup_12... - XXMAAXX",
                    "url": "https://github.com/OverX-System/data/commit/1cf37c0f2104ce60efd51d39a8df685c7f12146f",
                    "title": "[data:main] 1 new commit"
                }
            ]
        },
        {
            "author_id": 1364330195544313961,
            "author_name": "GitHub#0000",
            "author_avatar": "https://cdn.discordapp.com/avatars/1364330195544313961/df91181b3f1cf0ef1592fbe18e0962d7.png?size=1024",
            "is_bot": true,
            "content": "",
            "created_at": "2025-08-20T18:52:35.202000+00:00",
            "is_webhook": false,
            "attachments": [],
            "embeds": [
                {
                    "author": {
                        "name": "XXMAAXX",
                        "url": "https://github.com/XXMAAXX",
                        "icon_url": "https://avatars.githubusercontent.com/u/145601904?v=4",
                        "proxy_icon_url": "https://images-ext-1.discordapp.net/external/LrJoeFfhmNQcmM0wh9fZn3ntJnyJQBts-XWzR21NrcU/%3Fv%3D4/https/avatars.githubusercontent.com/u/145601904"
                    },
                    "flags": 0,
                    "color": 7506394,
                    "type": "rich",
                    "description": "[`f66b2ce`](https://github.com/OverX-System/data/commit/f66b2ce22cb8a74df0c8a91049baf66d6478aab4) Update data_channel_messages/messages_backup_12... - XXMAAXX",
                    "url": "https://github.com/OverX-System/data/commit/f66b2ce22cb8a74df0c8a91049baf66d6478aab4",
                    "title": "[data:main] 1 new commit"
                }
            ]
        }
    ],
    "1245104789017329695": [
        {
            "author_id": 1368624014364512287,
            "author_name": "GitHub#0000",
            "author_avatar": "https://cdn.discordapp.com/avatars/1368624014364512287/df91181b3f1cf0ef1592fbe18e0962d7.png?size=1024",
            "is_bot": true,
            "content": "",
            "created_at": "2025-08-20T18:52:45.128000+00:00",
            "is_webhook": false,
            "attachments": [],
            "embeds": [
                {
                    "author": {
                        "name": "XXMAAXX",
                        "url": "https://github.com/XXMAAXX",
                        "icon_url": "https://avatars.githubusercontent.com/u/145601904?v=4",
                        "proxy_icon_url": "https://images-ext-1.discordapp.net/external/LrJoeFfhmNQcmM0wh9fZn3ntJnyJQBts-XWzR21NrcU/%3Fv%3D4/https/avatars.githubusercontent.com/u/145601904"
                    },
                    "flags": 0,
                    "color": 7506394,
                    "type": "rich",
                    "description": "[`f69a41f`](https://github.com/OverX-System/data/commit/f69a41f20b108535e194760ce3d9b438510dfd01) Update data_channel_messages/messages_backup_12... - XXMAAXX",
                    "url": "https://github.com/OverX-System/data/commit/f69a41f20b108535e194760ce3d9b438510dfd01",
                    "title": "[data:main] 1 new commit"
                }
            ]
        },
        {
            "author_id": 1368624014364512287,
            "author_name": "GitHub#0000",
            "author_avatar": "https://cdn.discordapp.com/avatars/1368624014364512287/df91181b3f1cf0ef1592fbe18e0962d7.png?size=1024",
            "is_bot": true,
            "content": "",
            "created_at": "2025-08-20T18:52:43.714000+00:00",
            "is_webhook": false,
            "attachments": [],
            "embeds": [
                {
                    "author": {
                        "name": "XXMAAXX",
                        "url": "https://github.com/XXMAAXX",
                        "icon_url": "https://avatars.githubusercontent.com/u/145601904?v=4",
                        "proxy_icon_url": "https://images-ext-1.discordapp.net/external/LrJoeFfhmNQcmM0wh9fZn3ntJnyJQBts-XWzR21NrcU/%3Fv%3D4/https/avatars.githubusercontent.com/u/145601904"
                    },
                    "flags": 0,
                    "color": 7506394,
                    "type": "rich",
                    "description": "[`a37efbf`](https://github.com/OverX-System/data/commit/a37efbfd3e954b98eb995510d19b8613c3a09449) Update data_channel_messages/messages_backup_12... - XXMAAXX",
                    "url": "https://github.com/OverX-System/data/commit/a37efbfd3e954b98eb995510d19b8613c3a09449",
                    "title": "[data:main] 1 new commit"
                }
            ]
        },
        {
            "author_id": 1368624014364512287,
            "author_name": "GitHub#0000",
            "author_avatar": "https://cdn.discordapp.com/avatars/1368624014364512287/df91181b3f1cf0ef1592fbe18e0962d7.png?size=1024",
            "is_bot": true,
            "content": "",
            "created_at": "2025-08-20T18:52:42.253000+00:00",
            "is_webhook": false,
            "attachments": [],
            "embeds": [
                {
                    "author": {
                        "name": "XXMAAXX",
                        "url": "https://github.com/XXMAAXX",
                        "icon_url": "https://avatars.githubusercontent.com/u/145601904?v=4",
                        "proxy_icon_url": "https://images-ext-1.discordapp.net/external/LrJoeFfhmNQcmM0wh9fZn3ntJnyJQBts-XWzR21NrcU/%3Fv%3D4/https/avatars.githubusercontent.com/u/145601904"
                    },
                    "flags": 0,
                    "color": 7506394,
                    "type": "rich",
                    "description": "[`45d8306`](https://github.com/OverX-System/data/commit/45d830641d744dd73f9ab6a03f8c5c753db1e674) Update data_channel_messages/messages_backup_12... - XXMAAXX",
                    "url": "https://github.com/OverX-System/data/commit/45d830641d744dd73f9ab6a03f8c5c753db1e674",
                    "title": "[data:main] 1 new commit"
                }
            ]
        },
        {
            "author_id": 1368624014364512287,
            "author_name": "GitHub#0000",
            "author_avatar": "https://cdn.discordapp.com/avatars/1368624014364512287/df91181b3f1cf0ef1592fbe18e0962d7.png?size=1024",
            "is_bot": true,
            "content": "",
            "created_at": "2025-08-20T18:52:41.075000+00:00",
            "is_webhook": false,
            "attachments": [],
            "embeds": [
                {
                    "author": {
                        "name": "XXMAAXX",
                        "url": "https://github.com/XXMAAXX",
                        "icon_url": "https://avatars.githubusercontent.com/u/145601904?v=4",
                        "proxy_icon_url": "https://images-ext-1.discordapp.net/external/LrJoeFfhmNQcmM0wh9fZn3ntJnyJQBts-XWzR21NrcU/%3Fv%3D4/https/avatars.githubusercontent.com/u/145601904"
                    },
                    "flags": 0,
                    "color": 7506394,
                    "type": "rich",
                    "description": "[`0308638`](https://github.com/OverX-System/data/commit/03086389eee4e7250b2dbb74957e44dd23de1623) Update data_channel_messages/messages_backup_12... - XXMAAXX",
                    "url": "https://github.com/OverX-System/data/commit/03086389eee4e7250b2dbb74957e44dd23de1623",
                    "title": "[data:main] 1 new commit"
                }
            ]
        },
        {
            "author_id": 1368624014364512287,
            "author_name": "GitHub#0000",
            "author_avatar": "https://cdn.discordapp.com/avatars/1368624014364512287/df91181b3f1cf0ef1592fbe18e0962d7.png?size=1024",
            "is_bot": true,
            "content": "",
            "created_at": "2025-08-20T18:52:38.203000+00:00",
            "is_webhook": false,
            "attachments": [],
            "embeds": [
                {
                    "author": {
                        "name": "XXMAAXX",
                        "url": "https://github.com/XXMAAXX",
                        "icon_url": "https://avatars.githubusercontent.com/u/145601904?v=4",
                        "proxy_icon_url": "https://images-ext-1.discordapp.net/external/LrJoeFfhmNQcmM0wh9fZn3ntJnyJQBts-XWzR21NrcU/%3Fv%3D4/https/avatars.githubusercontent.com/u/145601904"
                    },
                    "flags": 0,
                    "color": 7506394,
                    "type": "rich",
                    "description": "[`1cf37c0`](https://github.com/OverX-System/data/commit/1cf37c0f2104ce60efd51d39a8df685c7f12146f) Update data_channel_messages/messages_backup_12... - XXMAAXX",
                    "url": "https://github.com/OverX-System/data/commit/1cf37c0f2104ce60efd51d39a8df685c7f12146f",
                    "title": "[data:main] 1 new commit"
                }
            ]
        }
    ]
}