{
    "1212061522851921940": [
        {
            "author_id": 1364330195544313961,
            "author_name": "GitHub#0000",
            "author_avatar": "https://cdn.discordapp.com/avatars/1364330195544313961/df91181b3f1cf0ef1592fbe18e0962d7.png?size=1024",
            "is_bot": true,
            "content": "",
            "created_at": "2025-08-20T18:56:28.941000+00:00",
            "is_webhook": false,
            "attachments": [],
            "embeds": [
                {
                    "author": {
                        "name": "XXMAAXX",
                        "url": "https://github.com/XXMAAXX",
                        "icon_url": "https://avatars.githubusercontent.com/u/145601904?v=4",
                        "proxy_icon_url": "https://images-ext-1.discordapp.net/external/LrJoeFfhmNQcmM0wh9fZn3ntJnyJQBts-XWzR21NrcU/%3Fv%3D4/https/avatars.githubusercontent.com/u/145601904"
                    },
                    "flags": 0,
                    "color": 7506394,
                    "type": "rich",
                    "description": "[`175e53f`](https://github.com/OverX-System/data/commit/175e53f213792b5f25a7cb55addb2654d95700ea) Update data_channel_messages/messages_backup_12... - XXMAAXX",
                    "url": "https://github.com/OverX-System/data/commit/175e53f213792b5f25a7cb55addb2654d95700ea",
                    "title": "[data:main] 1 new commit"
                }
            ]
        },
        {
            "author_id": 1364330195544313961,
            "author_name": "GitHub#0000",
            "author_avatar": "https://cdn.discordapp.com/avatars/1364330195544313961/df91181b3f1cf0ef1592fbe18e0962d7.png?size=1024",
            "is_bot": true,
            "content": "",
            "created_at": "2025-08-20T18:56:26.597000+00:00",
            "is_webhook": false,
            "attachments": [],
            "embeds": [
                {
                    "author": {
                        "name": "XXMAAXX",
                        "url": "https://github.com/XXMAAXX",
                        "icon_url": "https://avatars.githubusercontent.com/u/145601904?v=4",
                        "proxy_icon_url": "https://images-ext-1.discordapp.net/external/LrJoeFfhmNQcmM0wh9fZn3ntJnyJQBts-XWzR21NrcU/%3Fv%3D4/https/avatars.githubusercontent.com/u/145601904"
                    },
                    "flags": 0,
                    "color": 7506394,
                    "type": "rich",
                    "description": "[`d8a821f`](https://github.com/OverX-System/data/commit/d8a821ff7e1e77cd68b4b6788758826ba77295f7) Update rank data - XXMAAXX",
                    "url": "https://github.com/OverX-System/data/commit/d8a821ff7e1e77cd68b4b6788758826ba77295f7",
                    "title": "[data:main] 1 new commit"
                }
            ]
        },
        {
            "author_id": 1364330195544313961,
            "author_name": "GitHub#0000",
            "author_avatar": "https://cdn.discordapp.com/avatars/1364330195544313961/df91181b3f1cf0ef1592fbe18e0962d7.png?size=1024",
            "is_bot": true,
            "content": "",
            "created_at": "2025-08-20T18:56:24.762000+00:00",
            "is_webhook": false,
            "attachments": [],
            "embeds": [
                {
                    "author": {
                        "name": "XXMAAXX",
                        "url": "https://github.com/XXMAAXX",
                        "icon_url": "https://avatars.githubusercontent.com/u/145601904?v=4",
                        "proxy_icon_url": "https://images-ext-1.discordapp.net/external/LrJoeFfhmNQcmM0wh9fZn3ntJnyJQBts-XWzR21NrcU/%3Fv%3D4/https/avatars.githubusercontent.com/u/145601904"
                    },
                    "flags": 0,
                    "color": 7506394,
                    "type": "rich",
                    "description": "[`099452d`](https://github.com/OverX-System/data/commit/099452d871628cea4d7185a6842f4a5fb68c8ff2) Update data_channel_messages/messages_backup_12... - XXMAAXX",
                    "url": "https://github.com/OverX-System/data/commit/099452d871628cea4d7185a6842f4a5fb68c8ff2",
                    "title": "[data:main] 1 new commit"
                }
            ]
        },
        {
            "author_id": 1364330195544313961,
            "author_name": "GitHub#0000",
            "author_avatar": "https://cdn.discordapp.com/avatars/1364330195544313961/df91181b3f1cf0ef1592fbe18e0962d7.png?size=1024",
            "is_bot": true,
            "content": "",
            "created_at": "2025-08-20T18:56:23.251000+00:00",
            "is_webhook": false,
            "attachments": [],
            "embeds": [
                {
                    "author": {
                        "name": "XXMAAXX",
                        "url": "https://github.com/XXMAAXX",
                        "icon_url": "https://avatars.githubusercontent.com/u/145601904?v=4",
                        "proxy_icon_url": "https://images-ext-1.discordapp.net/external/LrJoeFfhmNQcmM0wh9fZn3ntJnyJQBts-XWzR21NrcU/%3Fv%3D4/https/avatars.githubusercontent.com/u/145601904"
                    },
                    "flags": 0,
                    "color": 7506394,
                    "type": "rich",
                    "description": "[`5db657d`](https://github.com/OverX-System/data/commit/5db657d88d663f50824af6c72a09d4075bd45f05) Update data_channel_messages/messages_backup_12... - XXMAAXX",
                    "url": "https://github.com/OverX-System/data/commit/5db657d88d663f50824af6c72a09d4075bd45f05",
                    "title": "[data:main] 1 new commit"
                }
            ]
        },
        {
            "author_id": 1364330195544313961,
            "author_name": "GitHub#0000",
            "author_avatar": "https://cdn.discordapp.com/avatars/1364330195544313961/df91181b3f1cf0ef1592fbe18e0962d7.png?size=1024",
            "is_bot": true,
            "content": "",
            "created_at": "2025-08-20T18:56:21.808000+00:00",
            "is_webhook": false,
            "attachments": [],
            "embeds": [
                {
                    "author": {
                        "name": "XXMAAXX",
                        "url": "https://github.com/XXMAAXX",
                        "icon_url": "https://avatars.githubusercontent.com/u/145601904?v=4",
                        "proxy_icon_url": "https://images-ext-1.discordapp.net/external/LrJoeFfhmNQcmM0wh9fZn3ntJnyJQBts-XWzR21NrcU/%3Fv%3D4/https/avatars.githubusercontent.com/u/145601904"
                    },
                    "flags": 0,
                    "color": 7506394,
                    "type": "rich",
                    "description": "[`7107080`](https://github.com/OverX-System/data/commit/710708038ae17a915a3a287090c09750f3c640f0) Update data_channel_messages/messages_backup_12... - XXMAAXX",
                    "url": "https://github.com/OverX-System/data/commit/710708038ae17a915a3a287090c09750f3c640f0",
                    "title": "[data:main] 1 new commit"
                }
            ]
        }
    ],
    "1245104789017329695": [
        {
            "author_id": 1368624014364512287,
            "author_name": "GitHub#0000",
            "author_avatar": "https://cdn.discordapp.com/avatars/1368624014364512287/df91181b3f1cf0ef1592fbe18e0962d7.png?size=1024",
            "is_bot": true,
            "content": "",
            "created_at": "2025-08-20T18:56:26.159000+00:00",
            "is_webhook": false,
            "attachments": [],
            "embeds": [
                {
                    "author": {
                        "name": "XXMAAXX",
                        "url": "https://github.com/XXMAAXX",
                        "icon_url": "https://avatars.githubusercontent.com/u/145601904?v=4",
                        "proxy_icon_url": "https://images-ext-1.discordapp.net/external/LrJoeFfhmNQcmM0wh9fZn3ntJnyJQBts-XWzR21NrcU/%3Fv%3D4/https/avatars.githubusercontent.com/u/145601904"
                    },
                    "flags": 0,
                    "color": 7506394,
                    "type": "rich",
                    "description": "[`c26638a`](https://github.com/OverX-System/data/commit/c26638aa4dcf841b16729a0a1e3c6816f45f4a25) Update data_channel_messages/messages_backup_12... - XXMAAXX",
                    "url": "https://github.com/OverX-System/data/commit/c26638aa4dcf841b16729a0a1e3c6816f45f4a25",
                    "title": "[data:main] 1 new commit"
                }
            ]
        },
        {
            "author_id": 1368624014364512287,
            "author_name": "GitHub#0000",
            "author_avatar": "https://cdn.discordapp.com/avatars/1368624014364512287/df91181b3f1cf0ef1592fbe18e0962d7.png?size=1024",
            "is_bot": true,
            "content": "",
            "created_at": "2025-08-20T18:56:24.819000+00:00",
            "is_webhook": false,
            "attachments": [],
            "embeds": [
                {
                    "author": {
                        "name": "XXMAAXX",
                        "url": "https://github.com/XXMAAXX",
                        "icon_url": "https://avatars.githubusercontent.com/u/145601904?v=4",
                        "proxy_icon_url": "https://images-ext-1.discordapp.net/external/LrJoeFfhmNQcmM0wh9fZn3ntJnyJQBts-XWzR21NrcU/%3Fv%3D4/https/avatars.githubusercontent.com/u/145601904"
                    },
                    "flags": 0,
                    "color": 7506394,
                    "type": "rich",
                    "description": "[`099452d`](https://github.com/OverX-System/data/commit/099452d871628cea4d7185a6842f4a5fb68c8ff2) Update data_channel_messages/messages_backup_12... - XXMAAXX",
                    "url": "https://github.com/OverX-System/data/commit/099452d871628cea4d7185a6842f4a5fb68c8ff2",
                    "title": "[data:main] 1 new commit"
                }
            ]
        },
        {
            "author_id": 1368624014364512287,
            "author_name": "GitHub#0000",
            "author_avatar": "https://cdn.discordapp.com/avatars/1368624014364512287/df91181b3f1cf0ef1592fbe18e0962d7.png?size=1024",
            "is_bot": true,
            "content": "",
            "created_at": "2025-08-20T18:56:23.775000+00:00",
            "is_webhook": false,
            "attachments": [],
            "embeds": [
                {
                    "author": {
                        "name": "XXMAAXX",
                        "url": "https://github.com/XXMAAXX",
                        "icon_url": "https://avatars.githubusercontent.com/u/145601904?v=4",
                        "proxy_icon_url": "https://images-ext-1.discordapp.net/external/LrJoeFfhmNQcmM0wh9fZn3ntJnyJQBts-XWzR21NrcU/%3Fv%3D4/https/avatars.githubusercontent.com/u/145601904"
                    },
                    "flags": 0,
                    "color": 7506394,
                    "type": "rich",
                    "description": "[`5db657d`](https://github.com/OverX-System/data/commit/5db657d88d663f50824af6c72a09d4075bd45f05) Update data_channel_messages/messages_backup_12... - XXMAAXX",
                    "url": "https://github.com/OverX-System/data/commit/5db657d88d663f50824af6c72a09d4075bd45f05",
                    "title": "[data:main] 1 new commit"
                }
            ]
        },
        {
            "author_id": 1368624014364512287,
            "author_name": "GitHub#0000",
            "author_avatar": "https://cdn.discordapp.com/avatars/1368624014364512287/df91181b3f1cf0ef1592fbe18e0962d7.png?size=1024",
            "is_bot": true,
            "content": "",
            "created_at": "2025-08-20T18:56:20.126000+00:00",
            "is_webhook": false,
            "attachments": [],
            "embeds": [
                {
                    "author": {
                        "name": "XXMAAXX",
                        "url": "https://github.com/XXMAAXX",
                        "icon_url": "https://avatars.githubusercontent.com/u/145601904?v=4",
                        "proxy_icon_url": "https://images-ext-1.discordapp.net/external/LrJoeFfhmNQcmM0wh9fZn3ntJnyJQBts-XWzR21NrcU/%3Fv%3D4/https/avatars.githubusercontent.com/u/145601904"
                    },
                    "flags": 0,
                    "color": 7506394,
                    "type": "rich",
                    "description": "[`2c65a39`](https://github.com/OverX-System/data/commit/2c65a39ae32e8a2658cbcdd1ae4221a42c989b07) Update data_channel_messages/messages_backup_12... - XXMAAXX",
                    "url": "https://github.com/OverX-System/data/commit/2c65a39ae32e8a2658cbcdd1ae4221a42c989b07",
                    "title": "[data:main] 1 new commit"
                }
            ]
        },
        {
            "author_id": 1368624014364512287,
            "author_name": "GitHub#0000",
            "author_avatar": "https://cdn.discordapp.com/avatars/1368624014364512287/df91181b3f1cf0ef1592fbe18e0962d7.png?size=1024",
            "is_bot": true,
            "content": "",
            "created_at": "2025-08-20T18:56:18.931000+00:00",
            "is_webhook": false,
            "attachments": [],
            "embeds": [
                {
                    "author": {
                        "name": "XXMAAXX",
                        "url": "https://github.com/XXMAAXX",
                        "icon_url": "https://avatars.githubusercontent.com/u/145601904?v=4",
                        "proxy_icon_url": "https://images-ext-1.discordapp.net/external/LrJoeFfhmNQcmM0wh9fZn3ntJnyJQBts-XWzR21NrcU/%3Fv%3D4/https/avatars.githubusercontent.com/u/145601904"
                    },
                    "flags": 0,
                    "color": 7506394,
                    "type": "rich",
                    "description": "[`cbcbe20`](https://github.com/OverX-System/data/commit/cbcbe20a10c038ef9b04ebfca62c473746768124) Update data_channel_messages/messages_backup_12... - XXMAAXX",
                    "url": "https://github.com/OverX-System/data/commit/cbcbe20a10c038ef9b04ebfca62c473746768124",
                    "title": "[data:main] 1 new commit"
                }
            ]
        }
    ]
}